<?xml version="1.0" encoding="iso-8859-1"?>

<TuningRoot>
    <Module name="sims4.color">
        <Class name="Color" enum_bit_flag="False" enum_locked="False">
            <EnumItem name="BLACK" enum_value="4278190080" />

            <EnumItem name="BLUE" enum_value="4278190335" />

            <EnumItem name="CYAN" enum_value="4278255615" />

            <EnumItem name="GREEN" enum_value="4278255360" />

            <EnumItem name="GREY" enum_value="4287137928" />

            <EnumItem name="MAGENTA" enum_value="4294902015" />

            <EnumItem name="ORANGE" enum_value="4294944000" />

            <EnumItem name="PEACH" enum_value="4294957753" />

            <EnumItem name="PINK" enum_value="4294951115" />

            <EnumItem name="RED" enum_value="4294901760" />

            <EnumItem name="WHITE" enum_value="4294967295" />

            <EnumItem name="YELLOW" enum_value="4294967040" />
        </Class>
    </Module>
</TuningRoot>